catnip/__init__.py
catnip/analysis.py
catnip/config.py
catnip/preparation.py
catnip/utils.py
catnip/visualisation.py
mo_catnip-1.0.0.dist-info/LICENSE
mo_catnip-1.0.0.dist-info/METADATA
mo_catnip-1.0.0.dist-info/WHEEL
mo_catnip-1.0.0.dist-info/top_level.txt
mo_catnip-1.0.0.dist-info/RECORD
