Metadata-Version: 2.1
Name: mo-catnip
Version: 1.0.0
Summary: Climate analysis tool
Home-page: https://github.com/MetOffice/CATNIP
Author: Met Office
Author-email: catnip@metoffice.gov.uk
License: BSD
Keywords: cmip,climate,analysis,rcp,iris
Platform: UNKNOWN
Classifier: Programming Language :: Python :: 3
Classifier: License :: OSI Approved :: BSD License
Classifier: Operating System :: OS Independent
Classifier: Development Status :: 5 - Production/Stable
Requires-Python: >=3.6
Requires-Dist: scitools-iris
Requires-Dist: numpy
